{
  "version": "3.0.3",
  "flags": {},
  "shapes": [
    {
      "kie_linking": [],
      "label": "gp",
      "score": null,
      "points": [
        [
          9.117647058823596,
          529.1176470588235
        ]
      ],
      "group_id": null,
      "description": "",
      "difficult": false,
      "shape_type": "point",
      "flags": {},
      "attributes": {}
    },
    {
      "kie_linking": [],
      "label": "gp",
      "score": null,
      "points": [
        [
          51.02941176470595,
          447.13235294117646
        ]
      ],
      "group_id": null,
      "description": "",
      "difficult": false,
      "shape_type": "point",
      "flags": {},
      "attributes": {}
    },
    {
      "kie_linking": [],
      "label": "gp",
      "score": null,
      "points": [
        [
          94.41176470588242,
          403.0147058823529
        ]
      ],
      "group_id": null,
      "description": "",
      "difficult": false,
      "shape_type": "point",
      "flags": {},
      "attributes": {}
    },
    {
      "kie_linking": [],
      "label": "gp",
      "score": null,
      "points": [
        [
          150.6617647058824,
          542.720588235294
        ]
      ],
      "group_id": null,
      "description": "",
      "difficult": false,
      "shape_type": "point",
      "flags": {},
      "attributes": {}
    },
    {
      "kie_linking": [],
      "label": "gp",
      "score": null,
      "points": [
        [
          298.82352941176475,
          582.4264705882352
        ]
      ],
      "group_id": null,
      "description": "",
      "difficult": false,
      "shape_type": "point",
      "flags": {},
      "attributes": {}
    },
    {
      "kie_linking": [],
      "label": "gp",
      "score": null,
      "points": [
        [
          201.39705882352948,
          406.3235294117647
        ]
      ],
      "group_id": null,
      "description": "",
      "difficult": false,
      "shape_type": "point",
      "flags": {},
      "attributes": {}
    },
    {
      "kie_linking": [],
      "label": "gp",
      "score": null,
      "points": [
        [
          213.89705882352948,
          390.1470588235294
        ]
      ],
      "group_id": null,
      "description": "",
      "difficult": false,
      "shape_type": "point",
      "flags": {},
      "attributes": {}
    },
    {
      "kie_linking": [],
      "label": "gp",
      "score": null,
      "points": [
        [
          282.2794117647059,
          368.0882352941176
        ]
      ],
      "group_id": null,
      "description": "",
      "difficult": false,
      "shape_type": "point",
      "flags": {},
      "attributes": {}
    },
    {
      "kie_linking": [],
      "label": "gp",
      "score": null,
      "points": [
        [
          309.48529411764713,
          402.6470588235294
        ]
      ],
      "group_id": null,
      "description": "",
      "difficult": false,
      "shape_type": "point",
      "flags": {},
      "attributes": {}
    },
    {
      "kie_linking": [],
      "label": "gp",
      "score": null,
      "points": [
        [
          386.32352941176475,
          418.45588235294116
        ]
      ],
      "group_id": null,
      "description": "",
      "difficult": false,
      "shape_type": "point",
      "flags": {},
      "attributes": {}
    },
    {
      "kie_linking": [],
      "label": "gp",
      "score": null,
      "points": [
        [
          448.82352941176475,
          376.5441176470588
        ]
      ],
      "group_id": null,
      "description": "",
      "difficult": false,
      "shape_type": "point",
      "flags": {},
      "attributes": {}
    },
    {
      "kie_linking": [],
      "label": "gp",
      "score": null,
      "points": [
        [
          510.9558823529412,
          365.5147058823529
        ]
      ],
      "group_id": null,
      "description": "",
      "difficult": false,
      "shape_type": "point",
      "flags": {},
      "attributes": {}
    },
    {
      "kie_linking": [],
      "label": "gp",
      "score": null,
      "points": [
        [
          485.5882352941177,
          440.5147058823529
        ]
      ],
      "group_id": null,
      "description": "",
      "difficult": false,
      "shape_type": "point",
      "flags": {},
      "attributes": {}
    },
    {
      "kie_linking": [],
      "label": "gp",
      "score": null,
      "points": [
        [
          442.2058823529412,
          585.0
        ]
      ],
      "group_id": null,
      "description": "",
      "difficult": false,
      "shape_type": "point",
      "flags": {},
      "attributes": {}
    },
    {
      "kie_linking": [],
      "label": "gp",
      "score": null,
      "points": [
        [
          307.2794117647059,
          327.27941176470586
        ]
      ],
      "group_id": null,
      "description": "",
      "difficult": false,
      "shape_type": "point",
      "flags": {},
      "attributes": {}
    },
    {
      "kie_linking": [],
      "label": "gp",
      "score": null,
      "points": [
        [
          76.764705882353,
          240.88235294117646
        ]
      ],
      "group_id": null,
      "description": "",
      "difficult": false,
      "shape_type": "point",
      "flags": {},
      "attributes": {}
    },
    {
      "kie_linking": [],
      "label": "gp",
      "score": null,
      "points": [
        [
          128.60294117647064,
          300.80882352941177
        ]
      ],
      "group_id": null,
      "description": "",
      "difficult": false,
      "shape_type": "point",
      "flags": {},
      "attributes": {}
    },
    {
      "kie_linking": [],
      "label": "gp",
      "score": null,
      "points": [
        [
          350.29411764705884,
          218.45588235294116
        ]
      ],
      "group_id": null,
      "description": "",
      "difficult": false,
      "shape_type": "point",
      "flags": {},
      "attributes": {}
    },
    {
      "kie_linking": [],
      "label": "gp",
      "score": null,
      "points": [
        [
          371.9852941176471,
          155.95588235294116
        ]
      ],
      "group_id": null,
      "description": "",
      "difficult": false,
      "shape_type": "point",
      "flags": {},
      "attributes": {}
    },
    {
      "kie_linking": [],
      "label": "gp",
      "score": null,
      "points": [
        [
          182.64705882352948,
          146.3970588235294
        ]
      ],
      "group_id": null,
      "description": "",
      "difficult": false,
      "shape_type": "point",
      "flags": {},
      "attributes": {}
    },
    {
      "kie_linking": [],
      "label": "gp",
      "score": null,
      "points": [
        [
          239.26470588235298,
          61.83823529411764
        ]
      ],
      "group_id": null,
      "description": "",
      "difficult": false,
      "shape_type": "point",
      "flags": {},
      "attributes": {}
    },
    {
      "kie_linking": [],
      "label": "gp",
      "score": null,
      "points": [
        [
          91.83823529411771,
          17.720588235294116
        ]
      ],
      "group_id": null,
      "description": "",
      "difficult": false,
      "shape_type": "point",
      "flags": {},
      "attributes": {}
    },
    {
      "kie_linking": [],
      "label": "gp",
      "score": null,
      "points": [
        [
          542.9411764705883,
          47.132352941176464
        ]
      ],
      "group_id": null,
      "description": "",
      "difficult": false,
      "shape_type": "point",
      "flags": {},
      "attributes": {}
    },
    {
      "kie_linking": [],
      "label": "gp",
      "score": null,
      "points": [
        [
          231.17647058823533,
          18.455882352941174
        ]
      ],
      "group_id": null,
      "description": "",
      "difficult": false,
      "shape_type": "point",
      "flags": {},
      "attributes": {}
    },
    {
      "kie_linking": [],
      "label": "gp",
      "score": null,
      "points": [
        [
          219.04411764705887,
          150.0735294117647
        ]
      ],
      "group_id": null,
      "description": "",
      "difficult": false,
      "shape_type": "point",
      "flags": {},
      "attributes": {}
    },
    {
      "kie_linking": [],
      "label": "gp",
      "score": null,
      "points": [
        [
          369.4117647058824,
          128.01470588235293
        ]
      ],
      "group_id": null,
      "description": "",
      "difficult": false,
      "shape_type": "point",
      "flags": {},
      "attributes": {}
    },
    {
      "kie_linking": [],
      "label": "gp",
      "score": null,
      "points": [
        [
          584.4852941176471,
          12.573529411764703
        ]
      ],
      "group_id": null,
      "description": "",
      "difficult": false,
      "shape_type": "point",
      "flags": {},
      "attributes": {}
    },
    {
      "kie_linking": [],
      "label": "gp",
      "score": null,
      "points": [
        [
          601.3970588235294,
          212.9411764705882
        ]
      ],
      "group_id": null,
      "description": "",
      "difficult": false,
      "shape_type": "point",
      "flags": {},
      "attributes": {}
    },
    {
      "kie_linking": [],
      "label": "gp",
      "score": null,
      "points": [
        [
          589.6323529411765,
          276.17647058823525
        ]
      ],
      "group_id": null,
      "description": "",
      "difficult": false,
      "shape_type": "point",
      "flags": {},
      "attributes": {}
    },
    {
      "kie_linking": [],
      "label": "gp",
      "score": null,
      "points": [
        [
          620.1470588235294,
          567.3529411764705
        ]
      ],
      "group_id": null,
      "description": "",
      "difficult": false,
      "shape_type": "point",
      "flags": {},
      "attributes": {}
    },
    {
      "kie_linking": [],
      "direction": 0.0,
      "label": "spinach",
      "score": null,
      "points": [
        [
          194.0,
          24.0
        ],
        [
          243.0,
          24.0
        ],
        [
          243.0,
          70.0
        ],
        [
          194.0,
          70.0
        ]
      ],
      "group_id": null,
      "description": "",
      "difficult": false,
      "shape_type": "rotation",
      "flags": {},
      "attributes": {}
    },
    {
      "kie_linking": [],
      "direction": 0.6,
      "label": "spinach",
      "score": null,
      "points": [
        [
          232.78873282218734,
          10.87913762987619
        ],
        [
          237.9724052271677,
          14.425478724508395
        ],
        [
          229.10863509749305,
          27.38161559888576
        ],
        [
          223.92496269251265,
          23.835274504253576
        ]
      ],
      "group_id": null,
      "description": "",
      "difficult": false,
      "shape_type": "rotation",
      "flags": {},
      "attributes": {}
    },
    {
      "kie_linking": [],
      "direction": 5.552278600022869,
      "label": "spinach",
      "score": null,
      "points": [
        [
          34.0,
          229.0
        ],
        [
          63.0,
          203.0
        ],
        [
          91.0,
          233.0
        ],
        [
          62.0,
          259.0
        ]
      ],
      "group_id": null,
      "description": "",
      "difficult": false,
      "shape_type": "rotation",
      "flags": {},
      "attributes": {}
    },
    {
      "kie_linking": [],
      "direction": 5.170988295728253,
      "label": "spinach",
      "score": null,
      "points": [
        [
          171.04343032911328,
          144.87342111653425
        ],
        [
          174.74697428333934,
          137.37189602529955
        ],
        [
          193.95995421063628,
          146.85744926773964
        ],
        [
          190.25641025641025,
          154.35897435897436
        ]
      ],
      "group_id": null,
      "description": "",
      "difficult": false,
      "shape_type": "rotation",
      "flags": {},
      "attributes": {}
    },
    {
      "kie_linking": [],
      "direction": 5.783185307179588,
      "label": "spinach",
      "score": null,
      "points": [
        [
          120.64163848932273,
          301.5744626564162
        ],
        [
          133.06669194936885,
          294.7866250147508
        ],
        [
          135.78313253012053,
          299.75903614457826
        ],
        [
          123.35807907007445,
          306.5468737862437
        ]
      ],
      "group_id": null,
      "description": "",
      "difficult": false,
      "shape_type": "rotation",
      "flags": {},
      "attributes": {}
    },
    {
      "kie_linking": [],
      "direction": 0.30000000000000004,
      "label": "spinach",
      "score": null,
      "points": [
        [
          182.3871016273264,
          358.81547804079884
        ],
        [
          222.40486380986664,
          371.19442251211564
        ],
        [
          207.23087693663857,
          420.24779693033315
        ],
        [
          167.21311475409834,
          407.86885245901635
        ]
      ],
      "group_id": null,
      "description": "",
      "difficult": false,
      "shape_type": "rotation",
      "flags": {},
      "attributes": {}
    },
    {
      "kie_linking": [],
      "direction": 5.483185307179589,
      "label": "spinach",
      "score": null,
      "points": [
        [
          132.35473436022906,
          397.58514590147354
        ],
        [
          165.32612907398183,
          363.63652662446736
        ],
        [
          210.34844389408062,
          407.3628561328298
        ],
        [
          177.37704918032784,
          441.311475409836
        ]
      ],
      "group_id": null,
      "description": "",
      "difficult": false,
      "shape_type": "rotation",
      "flags": {},
      "attributes": {}
    },
    {
      "kie_linking": [],
      "direction": 0.63,
      "label": "spinach",
      "score": null,
      "points": [
        [
          95.76954324911192,
          396.2316412964934
        ],
        [
          99.72887803984152,
          399.11845061041055
        ],
        [
          93.1304567508881,
          408.1683587035066
        ],
        [
          89.17112196015852,
          405.2815493895895
        ]
      ],
      "group_id": null,
      "description": "",
      "difficult": false,
      "shape_type": "rotation",
      "flags": {},
      "attributes": {}
    },
    {
      "kie_linking": [],
      "direction": 0.51,
      "label": "spinach",
      "score": null,
      "points": [
        [
          42.17126501564162,
          427.36202378297986
        ],
        [
          59.36820112688803,
          436.98127987919474
        ],
        [
          41.5725773488904,
          468.7956116850004
        ],
        [
          24.37564123764402,
          459.1763555887855
        ]
      ],
      "group_id": null,
      "description": "",
      "difficult": false,
      "shape_type": "rotation",
      "flags": {},
      "attributes": {}
    },
    {
      "kie_linking": [],
      "direction": 5.332638466367511,
      "label": "spinach",
      "score": null,
      "points": [
        [
          110.0,
          531.0
        ],
        [
          120.0,
          517.0
        ],
        [
          171.0,
          553.0
        ],
        [
          161.0,
          567.0
        ]
      ],
      "group_id": null,
      "description": "",
      "difficult": false,
      "shape_type": "rotation",
      "flags": {},
      "attributes": {}
    },
    {
      "kie_linking": [],
      "direction": 6.174524091338998,
      "label": "spinach",
      "score": null,
      "points": [
        [
          263.0,
          582.0
        ],
        [
          318.0,
          576.0
        ],
        [
          319.0,
          584.0
        ],
        [
          264.0,
          590.0
        ]
      ],
      "group_id": null,
      "description": "",
      "difficult": false,
      "shape_type": "rotation",
      "flags": {},
      "attributes": {}
    },
    {
      "kie_linking": [],
      "direction": 0.7,
      "label": "spinach",
      "score": null,
      "points": [
        [
          220.97266256491503,
          143.73450111083704
        ],
        [
          224.88010058912667,
          147.0256907560101
        ],
        [
          216.9,
          156.5
        ],
        [
          212.99256197578842,
          153.20881035482697
        ]
      ],
      "group_id": null,
      "description": "",
      "difficult": false,
      "shape_type": "rotation",
      "flags": {},
      "attributes": {}
    },
    {
      "kie_linking": [],
      "direction": 0.8999999999999999,
      "label": "spinach",
      "score": null,
      "points": [
        [
          353.65205982123314,
          209.60410109679376
        ],
        [
          357.95343137254895,
          215.02450980392157
        ],
        [
          346.16093228917606,
          224.38246098746163
        ],
        [
          341.8595607378602,
          218.9620522803337
        ]
      ],
      "group_id": null,
      "description": "",
      "difficult": false,
      "shape_type": "rotation",
      "flags": {},
      "attributes": {}
    },
    {
      "kie_linking": [],
      "direction": 5.761434752782945,
      "label": "spinach",
      "score": null,
      "points": [
        [
          325.6953193778404,
          117.78001906164712
        ],
        [
          349.4252873563218,
          104.13793103448273
        ],
        [
          381.8908875187112,
          160.610785536054
        ],
        [
          358.1609195402298,
          174.25287356321837
        ]
      ],
      "group_id": null,
      "description": "",
      "difficult": false,
      "shape_type": "rotation",
      "flags": {},
      "attributes": {}
    },
    {
      "kie_linking": [],
      "direction": 5.783185307179588,
      "label": "spinach",
      "score": null,
      "points": [
        [
          363.2044349486839,
          127.5685108367476
        ],
        [
          373.9908860212578,
          121.67584575922231
        ],
        [
          376.7634625668267,
          126.75101308339421
        ],
        [
          365.97701149425285,
          132.6436781609195
        ]
      ],
      "group_id": null,
      "description": "",
      "difficult": false,
      "shape_type": "rotation",
      "flags": {},
      "attributes": {}
    },
    {
      "kie_linking": [],
      "direction": 5.583185307179589,
      "label": "spinach",
      "score": null,
      "points": [
        [
          289.86643242744805,
          329.86431788663265
        ],
        [
          318.5126723512296,
          305.735922854874
        ],
        [
          325.72489160917473,
          314.29857126037615
        ],
        [
          297.07865168539325,
          338.4269662921348
        ]
      ],
      "group_id": null,
      "description": "",
      "difficult": false,
      "shape_type": "rotation",
      "flags": {},
      "attributes": {}
    },
    {
      "kie_linking": [],
      "direction": 5.583185307179589,
      "label": "broadleaf_weed",
      "score": null,
      "points": [
        [
          275.30605999238685,
          369.2491392792188
        ],
        [
          283.90084167674286,
          362.0098545338688
        ],
        [
          286.86296715741787,
          365.5266138165345
        ],
        [
          278.2681854730618,
          372.76589856188446
        ]
      ],
      "group_id": null,
      "description": "",
      "difficult": false,
      "shape_type": "rotation",
      "flags": {},
      "attributes": {}
    },
    {
      "kie_linking": [],
      "direction": 0.09739555984988074,
      "label": "spinach",
      "score": null,
      "points": [
        [
          308.41744109734793,
          370.67289926354835
        ],
        [
          318.20744068802014,
          371.6294281800015
        ],
        [
          312.49999999999994,
          430.04464285714283
        ],
        [
          302.7100004093278,
          429.0881139406897
        ]
      ],
      "group_id": null,
      "description": "",
      "difficult": false,
      "shape_type": "rotation",
      "flags": {},
      "attributes": {}
    },
    {
      "kie_linking": [],
      "direction": 0.6435011087932844,
      "label": "spinach",
      "score": null,
      "points": [
        [
          400.0,
          388.0
        ],
        [
          408.0,
          394.0
        ],
        [
          366.0,
          447.0
        ],
        [
          358.0,
          441.0
        ]
      ],
      "group_id": null,
      "description": "",
      "difficult": false,
      "shape_type": "rotation",
      "flags": {},
      "attributes": {}
    },
    {
      "kie_linking": [],
      "direction": 0.19739555984988075,
      "label": "spinach",
      "score": null,
      "points": [
        [
          431.0,
          350.0
        ],
        [
          456.0,
          355.0
        ],
        [
          448.0,
          394.0
        ],
        [
          424.0,
          389.0
        ]
      ],
      "group_id": null,
      "description": "",
      "difficult": false,
      "shape_type": "rotation",
      "flags": {},
      "attributes": {}
    },
    {
      "kie_linking": [],
      "direction": 0.19739555984988075,
      "label": "spinach",
      "score": null,
      "points": [
        [
          484.0,
          354.0
        ],
        [
          534.0,
          364.0
        ],
        [
          532.0,
          375.0
        ],
        [
          482.0,
          365.0
        ]
      ],
      "group_id": null,
      "description": "",
      "difficult": false,
      "shape_type": "rotation",
      "flags": {},
      "attributes": {}
    },
    {
      "kie_linking": [],
      "direction": 0.4002406570339742,
      "label": "spinach",
      "score": null,
      "points": [
        [
          469.2711908065842,
          428.4715863295304
        ],
        [
          497.6158940397351,
          440.4635761589404
        ],
        [
          490.86125952454154,
          456.4290759221252
        ],
        [
          462.5165562913907,
          444.4370860927152
        ]
      ],
      "group_id": null,
      "description": "",
      "difficult": false,
      "shape_type": "rotation",
      "flags": {},
      "attributes": {}
    },
    {
      "kie_linking": [],
      "direction": 5.683185307179588,
      "label": "spinach",
      "score": null,
      "points": [
        [
          434.5112090839257,
          586.4067145000172
        ],
        [
          445.2135602833871,
          579.0848421086658
        ],
        [
          447.97634285453785,
          583.1231901955748
        ],
        [
          437.2739916550765,
          590.4450625869263
        ]
      ],
      "group_id": null,
      "description": "",
      "difficult": false,
      "shape_type": "rotation",
      "flags": {},
      "attributes": {}
    },
    {
      "kie_linking": [],
      "direction": 0.0,
      "label": "spinach",
      "score": null,
      "points": [
        [
          526.0,
          7.0
        ],
        [
          545.0,
          7.0
        ],
        [
          545.0,
          53.0
        ],
        [
          526.0,
          53.0
        ]
      ],
      "group_id": null,
      "description": "",
      "difficult": false,
      "shape_type": "rotation",
      "flags": {},
      "attributes": {}
    },
    {
      "kie_linking": [],
      "direction": 0.1,
      "label": "spinach",
      "score": null,
      "points": [
        [
          575.6821017537181,
          6.850307675774886
        ],
        [
          594.8945656578436,
          8.777983941548868
        ],
        [
          594.1592920353982,
          16.106194690265482
        ],
        [
          574.9468281312726,
          14.1785184244915
        ]
      ],
      "group_id": null,
      "description": "",
      "difficult": false,
      "shape_type": "rotation",
      "flags": {},
      "attributes": {}
    },
    {
      "kie_linking": [],
      "direction": 0.2,
      "label": "spinach",
      "score": null,
      "points": [
        [
          563.4904731600802,
          192.15732039901658
        ],
        [
          589.5505773267412,
          197.4399650400001
        ],
        [
          587.3070325900514,
          208.50771869639797
        ],
        [
          561.2469284233906,
          203.22507405541444
        ]
      ],
      "group_id": null,
      "description": "",
      "difficult": false,
      "shape_type": "rotation",
      "flags": {},
      "attributes": {}
    },
    {
      "kie_linking": [],
      "direction": 5.683185307179588,
      "label": "spinach",
      "score": null,
      "points": [
        [
          582.1155119896644,
          213.13675153799238
        ],
        [
          623.8496660439821,
          184.5848805844311
        ],
        [
          632.3001917901667,
          196.93697981830837
        ],
        [
          590.566037735849,
          225.4888507718697
        ]
      ],
      "group_id": null,
      "description": "",
      "difficult": false,
      "shape_type": "rotation",
      "flags": {},
      "attributes": {}
    },
    {
      "kie_linking": [],
      "direction": 0.8999999999999999,
      "label": "spinach",
      "score": null,
      "points": [
        [
          581.0983343413731,
          259.5636381185993
        ],
        [
          594.5994579793667,
          276.57719001718
        ],
        [
          578.996282527881,
          288.9591078066914
        ],
        [
          565.4951588898874,
          271.94555590811075
        ]
      ],
      "group_id": null,
      "description": "",
      "difficult": false,
      "shape_type": "rotation",
      "flags": {},
      "attributes": {}
    }
  ],
  "imagePath": "IMG_20251212132811438_left.jpg",
  "imageData": null,
  "imageHeight": 640,
  "imageWidth": 640,
  "description": ""
}