{
  "version": "3.0.3",
  "flags": {},
  "shapes": [
    {
      "kie_linking": [],
      "label": "gp",
      "score": null,
      "points": [
        [
          14.478021978021957,
          129.1620879120879
        ]
      ],
      "group_id": null,
      "description": "",
      "difficult": false,
      "shape_type": "point",
      "flags": {},
      "attributes": {}
    },
    {
      "kie_linking": [],
      "label": "gp",
      "score": null,
      "points": [
        [
          38.92857142857139,
          155.9478021978022
        ]
      ],
      "group_id": null,
      "description": "",
      "difficult": false,
      "shape_type": "point",
      "flags": {},
      "attributes": {}
    },
    {
      "kie_linking": [],
      "label": "gp",
      "score": null,
      "points": [
        [
          69.14835164835165,
          145.37087912087912
        ]
      ],
      "group_id": null,
      "description": "",
      "difficult": false,
      "shape_type": "point",
      "flags": {},
      "attributes": {}
    },
    {
      "kie_linking": [],
      "label": "gp",
      "score": null,
      "points": [
        [
          66.40109890109886,
          238.9148351648352
        ]
      ],
      "group_id": null,
      "description": "",
      "difficult": false,
      "shape_type": "point",
      "flags": {},
      "attributes": {}
    },
    {
      "kie_linking": [],
      "label": "gp",
      "score": null,
      "points": [
        [
          76.84065934065933,
          204.71153846153845
        ]
      ],
      "group_id": null,
      "description": "",
      "difficult": false,
      "shape_type": "point",
      "flags": {},
      "attributes": {}
    },
    {
      "kie_linking": [],
      "label": "gp",
      "score": null,
      "points": [
        [
          94.28571428571428,
          39.05219780219782
        ]
      ],
      "group_id": null,
      "description": "",
      "difficult": false,
      "shape_type": "point",
      "flags": {},
      "attributes": {}
    },
    {
      "kie_linking": [],
      "label": "gp",
      "score": null,
      "points": [
        [
          121.07142857142856,
          11.167582417582427
        ]
      ],
      "group_id": null,
      "description": "",
      "difficult": false,
      "shape_type": "point",
      "flags": {},
      "attributes": {}
    },
    {
      "kie_linking": [],
      "label": "gp",
      "score": null,
      "points": [
        [
          117.87878787878788,
          184.33712121212122
        ]
      ],
      "group_id": null,
      "description": "",
      "difficult": false,
      "shape_type": "point",
      "flags": {},
      "attributes": {}
    },
    {
      "kie_linking": [],
      "label": "gp",
      "score": null,
      "points": [
        [
          295.530303030303,
          284.14772727272725
        ]
      ],
      "group_id": null,
      "description": "",
      "difficult": false,
      "shape_type": "point",
      "flags": {},
      "attributes": {}
    },
    {
      "kie_linking": [],
      "label": "gp",
      "score": null,
      "points": [
        [
          262.9545454545454,
          288.31439393939394
        ]
      ],
      "group_id": null,
      "description": "",
      "difficult": false,
      "shape_type": "point",
      "flags": {},
      "attributes": {}
    },
    {
      "kie_linking": [],
      "label": "gp",
      "score": null,
      "points": [
        [
          275.6439393939394,
          127.32954545454547
        ]
      ],
      "group_id": null,
      "description": "",
      "difficult": false,
      "shape_type": "point",
      "flags": {},
      "attributes": {}
    },
    {
      "kie_linking": [],
      "label": "gp",
      "score": null,
      "points": [
        [
          248.18181818181813,
          138.50378787878788
        ]
      ],
      "group_id": null,
      "description": "",
      "difficult": false,
      "shape_type": "point",
      "flags": {},
      "attributes": {}
    },
    {
      "kie_linking": [],
      "label": "gp",
      "score": null,
      "points": [
        [
          176.02272727272725,
          210.09469696969697
        ]
      ],
      "group_id": null,
      "description": "",
      "difficult": false,
      "shape_type": "point",
      "flags": {},
      "attributes": {}
    },
    {
      "kie_linking": [],
      "label": "gp",
      "score": null,
      "points": [
        [
          146.55667144906744,
          204.53371592539455
        ]
      ],
      "group_id": null,
      "description": "",
      "difficult": false,
      "shape_type": "point",
      "flags": {},
      "attributes": {}
    },
    {
      "kie_linking": [],
      "label": "gp",
      "score": null,
      "points": [
        [
          208.96700143472026,
          14.505021520803446
        ]
      ],
      "group_id": null,
      "description": "",
      "difficult": false,
      "shape_type": "point",
      "flags": {},
      "attributes": {}
    },
    {
      "kie_linking": [],
      "label": "gp",
      "score": null,
      "points": [
        [
          295.6652360515021,
          186.43061516452073
        ]
      ],
      "group_id": null,
      "description": "",
      "difficult": false,
      "shape_type": "point",
      "flags": {},
      "attributes": {}
    },
    {
      "label": "gp",
      "score": null,
      "points": [
        [
          127.10144927536231,
          6.231884057971012
        ]
      ],
      "group_id": null,
      "description": "",
      "difficult": false,
      "shape_type": "point",
      "flags": {},
      "attributes": {},
      "kie_linking": []
    },
    {
      "label": "gp",
      "score": null,
      "points": [
        [
          282.8112449799196,
          262.30923694779113
        ]
      ],
      "group_id": null,
      "description": "",
      "difficult": false,
      "shape_type": "point",
      "flags": {},
      "attributes": {},
      "kie_linking": []
    },
    {
      "label": "spinach",
      "score": null,
      "points": [
        [
          8.0,
          122.5
        ],
        [
          12.0,
          120.5
        ],
        [
          19.0,
          133.5
        ],
        [
          15.5,
          135.5
        ]
      ],
      "group_id": null,
      "description": "",
      "difficult": false,
      "shape_type": "rotation",
      "flags": {},
      "attributes": {},
      "kie_linking": [],
      "direction": 5.81953769817878
    },
    {
      "label": "spinach",
      "score": null,
      "points": [
        [
          30.0,
          155.0
        ],
        [
          31.0,
          151.0
        ],
        [
          49.5,
          155.0
        ],
        [
          48.5,
          158.5
        ]
      ],
      "group_id": null,
      "description": "",
      "difficult": false,
      "shape_type": "rotation",
      "flags": {},
      "attributes": {},
      "kie_linking": [],
      "direction": 4.957367643511553
    },
    {
      "label": "spinach",
      "score": null,
      "points": [
        [
          60.2681818181818,
          144.69545454545454
        ],
        [
          61.30454545454546,
          141.58636363636361
        ],
        [
          77.27272727272725,
          146.9090909090909
        ],
        [
          76.2363636363637,
          150.0181818181818
        ]
      ],
      "group_id": null,
      "description": "",
      "difficult": false,
      "shape_type": "rotation",
      "flags": {},
      "attributes": {},
      "kie_linking": [],
      "direction": 5.034139534781332
    },
    {
      "label": "spinach",
      "score": null,
      "points": [
        [
          109.0,
          23.0
        ],
        [
          112.5,
          27.0
        ],
        [
          90.5,
          44.0
        ],
        [
          87.0,
          40.0
        ]
      ],
      "group_id": null,
      "description": "",
      "difficult": false,
      "shape_type": "rotation",
      "flags": {},
      "attributes": {},
      "kie_linking": [],
      "direction": 0.8519663271732721
    },
    {
      "label": "spinach",
      "score": null,
      "points": [
        [
          115.30905804131726,
          5.618248474531185
        ],
        [
          119.29953901845363,
          2.2571127150302353
        ],
        [
          128.16920282824793,
          12.787548626918124
        ],
        [
          124.17872185111156,
          16.14868438641909
        ]
      ],
      "group_id": null,
      "description": "",
      "difficult": false,
      "shape_type": "rotation",
      "flags": {},
      "attributes": {},
      "kie_linking": [],
      "direction": 5.583185307179589
    },
    {
      "label": "spinach",
      "score": null,
      "points": [
        [
          123.12366716102457,
          6.798069931375423
        ],
        [
          123.49291881365951,
          0.731969920077649
        ],
        [
          139.97201492537312,
          1.7350746268656714
        ],
        [
          139.60276327273823,
          7.801174638163449
        ]
      ],
      "group_id": null,
      "description": "",
      "difficult": false,
      "shape_type": "rotation",
      "flags": {},
      "attributes": {},
      "kie_linking": [],
      "direction": 4.773185307179583
    },
    {
      "label": "spinach",
      "score": null,
      "points": [
        [
          64.16579161089902,
          226.08342619894037
        ],
        [
          68.29535172338768,
          225.7107590437291
        ],
        [
          70.2244522915401,
          247.08730550837674
        ],
        [
          66.09489217905144,
          247.45997266358796
        ]
      ],
      "group_id": null,
      "description": "",
      "difficult": false,
      "shape_type": "rotation",
      "flags": {},
      "attributes": {},
      "kie_linking": [],
      "direction": 6.193185307179586
    },
    {
      "label": "spinach",
      "score": null,
      "points": [
        [
          70.21893975451428,
          203.94776267250936
        ],
        [
          81.46341463414637,
          197.80487804878047
        ],
        [
          84.90301146499803,
          204.10101781529545
        ],
        [
          73.65853658536588,
          210.2439024390244
        ]
      ],
      "group_id": null,
      "description": "",
      "difficult": false,
      "shape_type": "rotation",
      "flags": {},
      "attributes": {},
      "kie_linking": [],
      "direction": 5.783185307179588
    },
    {
      "label": "spinach",
      "score": null,
      "points": [
        [
          114.88442979875254,
          180.14622808049896
        ],
        [
          117.79722254913497,
          178.981110980346
        ],
        [
          121.46757679180882,
          188.1569965870307
        ],
        [
          118.55478404142644,
          189.32211368718364
        ]
      ],
      "group_id": null,
      "description": "",
      "difficult": false,
      "shape_type": "rotation",
      "flags": {},
      "attributes": {},
      "kie_linking": [],
      "direction": 5.902678930067221
    },
    {
      "label": "broadleaf_weed",
      "score": null,
      "points": [
        [
          144.56562633537425,
          202.72288557233418
        ],
        [
          148.79017698199232,
          203.6233166235726
        ],
        [
          148.12778603268941,
          206.73105497771175
        ],
        [
          143.9032353860713,
          205.8306239264733
        ]
      ],
      "group_id": null,
      "description": "",
      "difficult": false,
      "shape_type": "rotation",
      "flags": {},
      "attributes": {},
      "kie_linking": [],
      "direction": 0.21000000000000005
    },
    {
      "label": "broadleaf_weed",
      "score": null,
      "points": [
        [
          174.30080431469275,
          208.54928539007966
        ],
        [
          175.92234528738112,
          207.86370886292093
        ],
        [
          177.5715409726883,
          211.76442347284132
        ],
        [
          175.95,
          212.45
        ]
      ],
      "group_id": null,
      "description": "",
      "difficult": false,
      "shape_type": "rotation",
      "flags": {},
      "attributes": {},
      "kie_linking": [],
      "direction": 5.883185307179588
    },
    {
      "label": "spinach",
      "score": null,
      "points": [
        [
          268.3933716799488,
          275.5961255868418
        ],
        [
          274.86333692812696,
          278.4854344420936
        ],
        [
          267.22511398959693,
          295.58953768820373
        ],
        [
          260.7551487414188,
          292.70022883295195
        ]
      ],
      "group_id": null,
      "description": "",
      "difficult": false,
      "shape_type": "rotation",
      "flags": {},
      "attributes": {},
      "kie_linking": [],
      "direction": 0.41999999999999993
    },
    {
      "label": "spinach",
      "score": null,
      "points": [
        [
          293.6594447502815,
          281.7920406099197
        ],
        [
          309.718875502008,
          280.18072289156623
        ],
        [
          310.1905261764317,
          284.88149745553704
        ],
        [
          294.1310954247051,
          286.49281517389056
        ]
      ],
      "group_id": null,
      "description": "",
      "difficult": false,
      "shape_type": "rotation",
      "flags": {},
      "attributes": {},
      "kie_linking": [],
      "direction": 6.183185307179587
    },
    {
      "label": "spinach",
      "score": null,
      "points": [
        [
          281.92110768759915,
          262.0453015920558
        ],
        [
          306.7179729100884,
          257.0187281623013
        ],
        [
          307.3961613887061,
          260.36433696216096
        ],
        [
          282.59929616621685,
          265.3909103919155
        ]
      ],
      "group_id": null,
      "description": "",
      "difficult": false,
      "shape_type": "rotation",
      "flags": {},
      "attributes": {},
      "kie_linking": [],
      "direction": 6.083185307179587
    },
    {
      "label": "sedge_weed",
      "score": null,
      "points": [
        [
          243.26030761323648,
          128.75578257612136
        ],
        [
          251.05414156660265,
          124.8943371372041
        ],
        [
          261.75417806738267,
          146.49099287175105
        ],
        [
          253.9603441140166,
          150.3524383106684
        ]
      ],
      "group_id": null,
      "description": "",
      "difficult": false,
      "shape_type": "rotation",
      "flags": {},
      "attributes": {},
      "kie_linking": [],
      "direction": 5.823185307179587
    },
    {
      "label": "spinach",
      "score": null,
      "points": [
        [
          204.5,
          7.5
        ],
        [
          215.5,
          2.5
        ],
        [
          219.5,
          12.0
        ],
        [
          208.5,
          16.5
        ]
      ],
      "group_id": null,
      "description": "",
      "difficult": false,
      "shape_type": "rotation",
      "flags": {},
      "attributes": {},
      "kie_linking": [],
      "direction": 5.85655781405271
    },
    {
      "label": "spinach",
      "score": null,
      "points": [
        [
          270.8467209757432,
          107.48737086424245
        ],
        [
          279.48504983388705,
          106.578073089701
        ],
        [
          282.83552541755796,
          138.40759113457426
        ],
        [
          274.197196559414,
          139.31688890911573
        ]
      ],
      "group_id": null,
      "description": "",
      "difficult": false,
      "shape_type": "rotation",
      "flags": {},
      "attributes": {},
      "kie_linking": [],
      "direction": 6.178308368449352
    },
    {
      "label": "spinach",
      "score": null,
      "points": [
        [
          292.66036331012356,
          172.81840339083212
        ],
        [
          307.42502064232656,
          168.25115966491725
        ],
        [
          315.9841695273251,
          195.92056115213384
        ],
        [
          301.219512195122,
          200.48780487804876
        ]
      ],
      "group_id": null,
      "description": "",
      "difficult": false,
      "shape_type": "rotation",
      "flags": {},
      "attributes": {},
      "kie_linking": [],
      "direction": 5.983185307179587
    },
    {
      "kie_linking": [],
      "label": "gp",
      "score": null,
      "points": [
        [
          405.8736059479554,
          193.92193308550185
        ]
      ],
      "group_id": null,
      "description": "",
      "difficult": false,
      "shape_type": "point",
      "flags": {},
      "attributes": {}
    },
    {
      "kie_linking": [],
      "label": "gp",
      "score": null,
      "points": [
        [
          401.97026022304834,
          204.51672862453532
        ]
      ],
      "group_id": null,
      "description": "",
      "difficult": false,
      "shape_type": "point",
      "flags": {},
      "attributes": {}
    },
    {
      "kie_linking": [],
      "label": "gp",
      "score": null,
      "points": [
        [
          423.7174721189591,
          220.68773234200742
        ]
      ],
      "group_id": null,
      "description": "",
      "difficult": false,
      "shape_type": "point",
      "flags": {},
      "attributes": {}
    },
    {
      "kie_linking": [],
      "label": "gp",
      "score": null,
      "points": [
        [
          464.6096654275093,
          226.44981412639405
        ]
      ],
      "group_id": null,
      "description": "",
      "difficult": false,
      "shape_type": "point",
      "flags": {},
      "attributes": {}
    },
    {
      "kie_linking": [],
      "label": "gp",
      "score": null,
      "points": [
        [
          477.99256505576204,
          227.19330855018586
        ]
      ],
      "group_id": null,
      "description": "",
      "difficult": false,
      "shape_type": "point",
      "flags": {},
      "attributes": {}
    },
    {
      "kie_linking": [],
      "label": "gp",
      "score": null,
      "points": [
        [
          562.9368029739777,
          270.5018587360595
        ]
      ],
      "group_id": null,
      "description": "",
      "difficult": false,
      "shape_type": "point",
      "flags": {},
      "attributes": {}
    },
    {
      "kie_linking": [],
      "label": "gp",
      "score": null,
      "points": [
        [
          366.8401486988848,
          177.56505576208178
        ]
      ],
      "group_id": null,
      "description": "",
      "difficult": false,
      "shape_type": "point",
      "flags": {},
      "attributes": {}
    },
    {
      "kie_linking": [],
      "label": "gp",
      "score": null,
      "points": [
        [
          440.26022304832713,
          297.8252788104089
        ]
      ],
      "group_id": null,
      "description": "",
      "difficult": false,
      "shape_type": "point",
      "flags": {},
      "attributes": {}
    },
    {
      "kie_linking": [],
      "label": "gp",
      "score": null,
      "points": [
        [
          555.3159851301116,
          287.41635687732344
        ]
      ],
      "group_id": null,
      "description": "",
      "difficult": false,
      "shape_type": "point",
      "flags": {},
      "attributes": {}
    },
    {
      "kie_linking": [],
      "label": "gp",
      "score": null,
      "points": [
        [
          408.10408921933083,
          89.27509293680298
        ]
      ],
      "group_id": null,
      "description": "",
      "difficult": false,
      "shape_type": "point",
      "flags": {},
      "attributes": {}
    },
    {
      "kie_linking": [],
      "label": "gp",
      "score": null,
      "points": [
        [
          591.7472118959108,
          111.76579925650557
        ]
      ],
      "group_id": null,
      "description": "",
      "difficult": false,
      "shape_type": "point",
      "flags": {},
      "attributes": {}
    },
    {
      "kie_linking": [],
      "label": "gp",
      "score": null,
      "points": [
        [
          544.1635687732341,
          132.95539033457248
        ]
      ],
      "group_id": null,
      "description": "",
      "difficult": false,
      "shape_type": "point",
      "flags": {},
      "attributes": {}
    },
    {
      "kie_linking": [],
      "label": "gp",
      "score": null,
      "points": [
        [
          578.9219330855019,
          27.565055762081784
        ]
      ],
      "group_id": null,
      "description": "",
      "difficult": false,
      "shape_type": "point",
      "flags": {},
      "attributes": {}
    },
    {
      "kie_linking": [],
      "label": "gp",
      "score": null,
      "points": [
        [
          573.5315985130112,
          44.29368029739777
        ]
      ],
      "group_id": null,
      "description": "",
      "difficult": false,
      "shape_type": "point",
      "flags": {},
      "attributes": {}
    },
    {
      "kie_linking": [],
      "label": "gp",
      "score": null,
      "points": [
        [
          603.8289962825279,
          81.28252788104089
        ]
      ],
      "group_id": null,
      "description": "",
      "difficult": false,
      "shape_type": "point",
      "flags": {},
      "attributes": {}
    },
    {
      "kie_linking": [],
      "label": "gp",
      "score": null,
      "points": [
        [
          531.7100371747213,
          17.52788104089219
        ]
      ],
      "group_id": null,
      "description": "",
      "difficult": false,
      "shape_type": "point",
      "flags": {},
      "attributes": {}
    },
    {
      "kie_linking": [],
      "label": "gp",
      "score": null,
      "points": [
        [
          400.1115241635688,
          39.83271375464684
        ]
      ],
      "group_id": null,
      "description": "",
      "difficult": false,
      "shape_type": "point",
      "flags": {},
      "attributes": {}
    },
    {
      "kie_linking": [],
      "label": "gp",
      "score": null,
      "points": [
        [
          347.5092936802974,
          3.7732342007434916
        ]
      ],
      "group_id": null,
      "description": "",
      "difficult": false,
      "shape_type": "point",
      "flags": {},
      "attributes": {}
    },
    {
      "kie_linking": [],
      "label": "gp",
      "score": null,
      "points": [
        [
          332.0817843866171,
          40.3903345724907
        ]
      ],
      "group_id": null,
      "description": "",
      "difficult": false,
      "shape_type": "point",
      "flags": {},
      "attributes": {}
    },
    {
      "kie_linking": [],
      "label": "gp",
      "score": null,
      "points": [
        [
          626.3295880149813,
          77.00374531835206
        ]
      ],
      "group_id": null,
      "description": "",
      "difficult": false,
      "shape_type": "point",
      "flags": {},
      "attributes": {}
    },
    {
      "label": "gp",
      "score": null,
      "points": [
        [
          397.9255319148936,
          56.01063829787236
        ]
      ],
      "group_id": null,
      "description": "",
      "difficult": false,
      "shape_type": "point",
      "flags": {},
      "attributes": {},
      "kie_linking": []
    },
    {
      "label": "spinach",
      "score": null,
      "points": [
        [
          414.0,
          76.5
        ],
        [
          419.0,
          84.5
        ],
        [
          400.0,
          96.5
        ],
        [
          395.0,
          89.0
        ]
      ],
      "group_id": null,
      "description": "",
      "difficult": false,
      "shape_type": "rotation",
      "flags": {},
      "attributes": {},
      "kie_linking": [],
      "direction": 1.012197011451334
    },
    {
      "label": "spinach",
      "score": null,
      "points": [
        [
          580.5,
          11.5
        ],
        [
          587.0,
          15.0
        ],
        [
          576.0,
          34.0
        ],
        [
          569.5,
          30.0
        ]
      ],
      "group_id": null,
      "description": "",
      "difficult": false,
      "shape_type": "rotation",
      "flags": {},
      "attributes": {},
      "kie_linking": [],
      "direction": 0.49394136891958124
    },
    {
      "label": "spinach",
      "score": null,
      "points": [
        [
          562.0,
          36.0
        ],
        [
          564.5,
          33.0
        ],
        [
          579.0,
          45.5
        ],
        [
          576.5,
          48.5
        ]
      ],
      "group_id": null,
      "description": "",
      "difficult": false,
      "shape_type": "rotation",
      "flags": {},
      "attributes": {},
      "kie_linking": [],
      "direction": 5.4071272565813935
    },
    {
      "label": "spinach",
      "score": null,
      "points": [
        [
          388.6111111111111,
          58.472222222222214
        ],
        [
          396.88333921751854,
          47.0889565493129
        ],
        [
          402.4180317423351,
          51.111021954767764
        ],
        [
          394.1458036359276,
          62.49428762767707
        ]
      ],
      "group_id": null,
      "description": "",
      "difficult": false,
      "shape_type": "rotation",
      "flags": {},
      "attributes": {},
      "kie_linking": [],
      "direction": 5.340811084202843
    },
    {
      "label": "sedge_weed",
      "score": null,
      "points": [
        [
          394.79892044430574,
          37.44471951446144
        ],
        [
          398.69565217391306,
          33.4324942791762
        ],
        [
          403.1644662833831,
          37.77267178988636
        ],
        [
          399.26773455377577,
          41.784897025171624
        ]
      ],
      "group_id": null,
      "description": "",
      "difficult": false,
      "shape_type": "rotation",
      "flags": {},
      "attributes": {},
      "kie_linking": [],
      "direction": 5.483185307179589
    },
    {
      "label": "broadleaf_weed",
      "score": null,
      "points": [
        [
          328.166399957124,
          39.818711137268814
        ],
        [
          335.4338965839702,
          39.08952924633209
        ],
        [
          335.6356736242884,
          41.10056925996204
        ],
        [
          328.3681769974423,
          41.829751150898765
        ]
      ],
      "group_id": null,
      "description": "",
      "difficult": false,
      "shape_type": "rotation",
      "flags": {},
      "attributes": {},
      "kie_linking": [],
      "direction": 6.183185307179587
    },
    {
      "label": "spinach",
      "score": null,
      "points": [
        [
          365.96558823529415,
          169.5791176470588
        ],
        [
          370.36764705882354,
          175.4485294117647
        ],
        [
          358.1888235294118,
          184.58264705882348
        ],
        [
          353.7867647058824,
          178.71323529411762
        ]
      ],
      "group_id": null,
      "description": "",
      "difficult": false,
      "shape_type": "rotation",
      "flags": {},
      "attributes": {},
      "kie_linking": [],
      "direction": 0.9272952180016123
    },
    {
      "label": "spinach",
      "score": null,
      "points": [
        [
          388.6681133512125,
          195.23253393956116
        ],
        [
          412.56720219294755,
          189.1300946792803
        ],
        [
          413.89705882352945,
          194.33823529411762
        ],
        [
          389.9979699817944,
          200.4406745543985
        ]
      ],
      "group_id": null,
      "description": "",
      "difficult": false,
      "shape_type": "rotation",
      "flags": {},
      "attributes": {},
      "kie_linking": [],
      "direction": 6.033185307179586
    },
    {
      "label": "spinach",
      "score": null,
      "points": [
        [
          387.31941463567154,
          205.2197760932859
        ],
        [
          410.7744200939138,
          200.4652111039895
        ],
        [
          411.50735294117646,
          204.08088235294116
        ],
        [
          388.05234748293424,
          208.83544734223753
        ]
      ],
      "group_id": null,
      "description": "",
      "difficult": false,
      "shape_type": "rotation",
      "flags": {},
      "attributes": {},
      "kie_linking": [],
      "direction": 6.083185307179587
    },
    {
      "label": "spinach",
      "score": null,
      "points": [
        [
          409.0,
          212.0
        ],
        [
          425.0,
          211.0
        ],
        [
          426.0,
          230.5
        ],
        [
          410.5,
          231.5
        ]
      ],
      "group_id": null,
      "description": "",
      "difficult": false,
      "shape_type": "rotation",
      "flags": {},
      "attributes": {},
      "kie_linking": [],
      "direction": 6.220766497183629
    },
    {
      "label": "spinach",
      "score": null,
      "points": [
        [
          446.9942343042384,
          232.80884641980717
        ],
        [
          474.47180532157614,
          217.79778095817602
        ],
        [
          477.5762553086679,
          223.4804385422179
        ],
        [
          450.09868429133013,
          238.49150400384906
        ]
      ],
      "group_id": null,
      "description": "",
      "difficult": false,
      "shape_type": "rotation",
      "flags": {},
      "attributes": {},
      "kie_linking": [],
      "direction": 5.783185307179588
    },
    {
      "label": "spinach",
      "score": null,
      "points": [
        [
          465.75076639188615,
          234.80112889404097
        ],
        [
          487.27322846106074,
          223.04335427808232
        ],
        [
          485.0857355092545,
          219.0391752884685
        ],
        [
          463.56327344007997,
          230.79694990442718
        ]
      ],
      "group_id": null,
      "description": "",
      "difficult": false,
      "shape_type": "rotation",
      "flags": {},
      "attributes": {},
      "kie_linking": [],
      "direction": 5.783185307179588
    },
    {
      "label": "spinach",
      "score": null,
      "points": [
        [
          445.5,
          286.0
        ],
        [
          449.5,
          291.5
        ],
        [
          427.5,
          309.0
        ],
        [
          423.5,
          303.5
        ]
      ],
      "group_id": null,
      "description": "",
      "difficult": false,
      "shape_type": "rotation",
      "flags": {},
      "attributes": {},
      "kie_linking": [],
      "direction": 0.9420000403794636
    },
    {
      "label": "spinach",
      "score": null,
      "points": [
        [
          550.6122448979592,
          282.85714285714283
        ],
        [
          562.5795918367347,
          288.8408163265306
        ],
        [
          559.0,
          296.0
        ],
        [
          547.0326530612244,
          290.0163265306122
        ]
      ],
      "group_id": null,
      "description": "",
      "difficult": false,
      "shape_type": "rotation",
      "flags": {},
      "attributes": {},
      "kie_linking": [],
      "direction": 0.46364760900080615
    },
    {
      "label": "spinach",
      "score": null,
      "points": [
        [
          554.9062031571555,
          267.7946356086879
        ],
        [
          574.3878749555066,
          270.00426613159004
        ],
        [
          573.7673860840654,
          275.47493664535114
        ],
        [
          554.2857142857142,
          273.265306122449
        ]
      ],
      "group_id": null,
      "description": "",
      "difficult": false,
      "shape_type": "rotation",
      "flags": {},
      "attributes": {},
      "kie_linking": [],
      "direction": 0.11293834957939711
    },
    {
      "label": "spinach",
      "score": null,
      "points": [
        [
          537.8314122495126,
          131.5399540981185
        ],
        [
          550.3252428316234,
          130.28638970357122
        ],
        [
          550.6527506464151,
          133.55054363943805
        ],
        [
          538.1589200643042,
          134.80410803398533
        ]
      ],
      "group_id": null,
      "description": "",
      "difficult": false,
      "shape_type": "rotation",
      "flags": {},
      "attributes": {},
      "kie_linking": [],
      "direction": 6.183185307179587
    },
    {
      "label": "spinach",
      "score": null,
      "points": [
        [
          578.8861003861003,
          101.88610038610038
        ],
        [
          587.3861003861003,
          98.38610038610038
        ],
        [
          594.3861003861003,
          116.3861003861004
        ],
        [
          585.8861003861003,
          119.8861003861004
        ]
      ],
      "group_id": null,
      "description": "",
      "difficult": false,
      "shape_type": "rotation",
      "flags": {},
      "attributes": {},
      "kie_linking": [],
      "direction": 5.892578263481899
    },
    {
      "label": "sedge_weed",
      "score": null,
      "points": [
        [
          618.6959002921841,
          67.86007121986852
        ],
        [
          622.0,
          65.5
        ],
        [
          635.6182888970052,
          84.5656044558072
        ],
        [
          632.3141891891892,
          86.92567567567568
        ]
      ],
      "group_id": null,
      "description": "",
      "difficult": false,
      "shape_type": "rotation",
      "flags": {},
      "attributes": {},
      "kie_linking": [],
      "direction": 5.662935821196765
    },
    {
      "label": "spinach",
      "score": null,
      "points": [
        [
          604.0948918408924,
          70.99054983305179
        ],
        [
          609.5749967452266,
          76.11524907002928
        ],
        [
          601.307807607037,
          84.95578031805867
        ],
        [
          595.8277027027027,
          79.83108108108108
        ]
      ],
      "group_id": null,
      "description": "",
      "difficult": false,
      "shape_type": "rotation",
      "flags": {},
      "attributes": {},
      "kie_linking": [],
      "direction": 0.7518970546041639
    },
    {
      "kie_linking": [],
      "label": "gp",
      "score": null,
      "points": [
        [
          46.62921348314609,
          619.8501872659176
        ]
      ],
      "group_id": null,
      "description": "",
      "difficult": false,
      "shape_type": "point",
      "flags": {},
      "attributes": {}
    },
    {
      "kie_linking": [],
      "label": "gp",
      "score": null,
      "points": [
        [
          10.86142322097379,
          552.2471910112359
        ]
      ],
      "group_id": null,
      "description": "",
      "difficult": false,
      "shape_type": "point",
      "flags": {},
      "attributes": {}
    },
    {
      "kie_linking": [],
      "label": "gp",
      "score": null,
      "points": [
        [
          130.7116104868914,
          528.6516853932585
        ]
      ],
      "group_id": null,
      "description": "",
      "difficult": false,
      "shape_type": "point",
      "flags": {},
      "attributes": {}
    },
    {
      "kie_linking": [],
      "label": "gp",
      "score": null,
      "points": [
        [
          145.8801498127341,
          534.8314606741574
        ]
      ],
      "group_id": null,
      "description": "",
      "difficult": false,
      "shape_type": "point",
      "flags": {},
      "attributes": {}
    },
    {
      "kie_linking": [],
      "label": "gp",
      "score": null,
      "points": [
        [
          138.20224719101122,
          387.26591760299624
        ]
      ],
      "group_id": null,
      "description": "",
      "difficult": false,
      "shape_type": "point",
      "flags": {},
      "attributes": {}
    },
    {
      "kie_linking": [],
      "label": "gp",
      "score": null,
      "points": [
        [
          3.932584269662925,
          323.4082397003745
        ]
      ],
      "group_id": null,
      "description": "",
      "difficult": false,
      "shape_type": "point",
      "flags": {},
      "attributes": {}
    },
    {
      "kie_linking": [],
      "label": "gp",
      "score": null,
      "points": [
        [
          111.98501872659176,
          345.5056179775281
        ]
      ],
      "group_id": null,
      "description": "",
      "difficult": false,
      "shape_type": "point",
      "flags": {},
      "attributes": {}
    },
    {
      "kie_linking": [],
      "label": "gp",
      "score": null,
      "points": [
        [
          65.60000000000002,
          358.0
        ]
      ],
      "group_id": null,
      "description": "",
      "difficult": false,
      "shape_type": "point",
      "flags": {},
      "attributes": {}
    },
    {
      "kie_linking": [],
      "label": "gp",
      "score": null,
      "points": [
        [
          142.68939393939394,
          479.33712121212125
        ]
      ],
      "group_id": null,
      "description": "",
      "difficult": false,
      "shape_type": "point",
      "flags": {},
      "attributes": {}
    },
    {
      "kie_linking": [],
      "label": "gp",
      "score": null,
      "points": [
        [
          238.90151515151513,
          629.3371212121212
        ]
      ],
      "group_id": null,
      "description": "",
      "difficult": false,
      "shape_type": "point",
      "flags": {},
      "attributes": {}
    },
    {
      "kie_linking": [],
      "label": "gp",
      "score": null,
      "points": [
        [
          282.6515151515151,
          540.1325757575758
        ]
      ],
      "group_id": null,
      "description": "",
      "difficult": false,
      "shape_type": "point",
      "flags": {},
      "attributes": {}
    },
    {
      "kie_linking": [],
      "label": "gp",
      "score": null,
      "points": [
        [
          202.15909090909088,
          536.344696969697
        ]
      ],
      "group_id": null,
      "description": "",
      "difficult": false,
      "shape_type": "point",
      "flags": {},
      "attributes": {}
    },
    {
      "kie_linking": [],
      "label": "gp",
      "score": null,
      "points": [
        [
          195.15151515151513,
          532.935606060606
        ]
      ],
      "group_id": null,
      "description": "",
      "difficult": false,
      "shape_type": "point",
      "flags": {},
      "attributes": {}
    },
    {
      "kie_linking": [],
      "label": "gp",
      "score": null,
      "points": [
        [
          162.38636363636363,
          545.0568181818182
        ]
      ],
      "group_id": null,
      "description": "",
      "difficult": false,
      "shape_type": "point",
      "flags": {},
      "attributes": {}
    },
    {
      "kie_linking": [],
      "label": "gp",
      "score": null,
      "points": [
        [
          141.55303030303025,
          561.9128787878788
        ]
      ],
      "group_id": null,
      "description": "",
      "difficult": false,
      "shape_type": "point",
      "flags": {},
      "attributes": {}
    },
    {
      "kie_linking": [],
      "label": "gp",
      "score": null,
      "points": [
        [
          276.4015151515151,
          465.7007575757576
        ]
      ],
      "group_id": null,
      "description": "",
      "difficult": false,
      "shape_type": "point",
      "flags": {},
      "attributes": {}
    },
    {
      "kie_linking": [],
      "label": "gp",
      "score": null,
      "points": [
        [
          26.260869565217376,
          329.39130434782606
        ]
      ],
      "group_id": null,
      "description": "",
      "difficult": false,
      "shape_type": "point",
      "flags": {},
      "attributes": {}
    },
    {
      "label": "broadleaf_weed",
      "score": null,
      "points": [
        [
          22.274838945075544,
          327.16477546556143
        ],
        [
          31.891634980988613,
          323.0988593155894
        ],
        [
          33.92524203884898,
          327.9087923223905
        ],
        [
          24.308446002935966,
          331.97470847236264
        ]
      ],
      "group_id": null,
      "description": "",
      "difficult": false,
      "shape_type": "rotation",
      "flags": {},
      "attributes": {},
      "kie_linking": [],
      "direction": 5.883185307179588
    },
    {
      "label": "spinach",
      "score": null,
      "points": [
        [
          62.628129101933155,
          358.16902174679296
        ],
        [
          67.16076965951515,
          357.2502100184175
        ],
        [
          68.76039933444258,
          365.14143094841927
        ],
        [
          64.22775877686058,
          366.06024267679476
        ]
      ],
      "group_id": null,
      "description": "",
      "difficult": false,
      "shape_type": "rotation",
      "flags": {},
      "attributes": {},
      "kie_linking": [],
      "direction": 6.083185307179587
    },
    {
      "label": "spinach",
      "score": null,
      "points": [
        [
          4.5,
          545.5
        ],
        [
          10.0,
          543.5
        ],
        [
          17.0,
          561.5
        ],
        [
          11.5,
          563.5
        ]
      ],
      "group_id": null,
      "description": "",
      "difficult": false,
      "shape_type": "rotation",
      "flags": {},
      "attributes": {},
      "kie_linking": [],
      "direction": 5.93441430359568
    },
    {
      "label": "spinach",
      "score": null,
      "points": [
        [
          36.5,
          618.5
        ],
        [
          41.5,
          612.5
        ],
        [
          58.0,
          626.5
        ],
        [
          53.5,
          632.5
        ]
      ],
      "group_id": null,
      "description": "",
      "difficult": false,
      "shape_type": "rotation",
      "flags": {},
      "attributes": {},
      "kie_linking": [],
      "direction": 5.4071272565813935
    },
    {
      "label": "spinach",
      "score": null,
      "points": [
        [
          126.07324930675315,
          338.586758156035
        ],
        [
          123.65808823529409,
          334.82536764705884
        ],
        [
          109.06379550400146,
          344.1962552446059
        ],
        [
          111.47895657546059,
          347.957645753582
        ]
      ],
      "group_id": null,
      "description": "",
      "difficult": false,
      "shape_type": "rotation",
      "flags": {},
      "attributes": {},
      "kie_linking": [],
      "direction": 0.9999999999999999
    },
    {
      "label": "spinach",
      "score": null,
      "points": [
        [
          134.3721431655494,
          383.989027026804
        ],
        [
          139.4922178265793,
          378.2769061079089
        ],
        [
          150.95340799436315,
          388.55017416307203
        ],
        [
          145.83333333333331,
          394.2622950819672
        ]
      ],
      "group_id": null,
      "description": "",
      "difficult": false,
      "shape_type": "rotation",
      "flags": {},
      "attributes": {},
      "kie_linking": [],
      "direction": 5.443185307179586
    },
    {
      "label": "spinach",
      "score": null,
      "points": [
        [
          140.0,
          468.5
        ],
        [
          147.3628368835631,
          467.36725586406726
        ],
        [
          150.25188916876573,
          486.1460957178841
        ],
        [
          142.88905228520258,
          487.2788398538169
        ]
      ],
      "group_id": null,
      "description": "",
      "difficult": false,
      "shape_type": "rotation",
      "flags": {},
      "attributes": {},
      "kie_linking": [],
      "direction": 6.130535978784321
    },
    {
      "label": "spinach",
      "score": null,
      "points": [
        [
          126.43277547468301,
          519.5865686015984
        ],
        [
          133.03478609603246,
          516.7952832808545
        ],
        [
          141.74904270713512,
          537.4064383914085
        ],
        [
          135.14703208578567,
          540.1977237121524
        ]
      ],
      "group_id": null,
      "description": "",
      "difficult": false,
      "shape_type": "rotation",
      "flags": {},
      "attributes": {},
      "kie_linking": [],
      "direction": 5.883185307179588
    },
    {
      "label": "spinach",
      "score": null,
      "points": [
        [
          140.9110390837351,
          525.8844384967715
        ],
        [
          146.52502165434163,
          523.5108847358048
        ],
        [
          155.50699300699296,
          544.7552447552448
        ],
        [
          149.89301043638642,
          547.1287985162114
        ]
      ],
      "group_id": null,
      "description": "",
      "difficult": false,
      "shape_type": "rotation",
      "flags": {},
      "attributes": {},
      "kie_linking": [],
      "direction": 5.883185307179588
    },
    {
      "label": "broadleaf_weed",
      "score": null,
      "points": [
        [
          138.50798258345424,
          561.4262906904416
        ],
        [
          143.5,
          560.0
        ],
        [
          144.11289653742483,
          562.145137880987
        ],
        [
          139.12087912087912,
          563.5714285714286
        ]
      ],
      "group_id": null,
      "description": "",
      "difficult": false,
      "shape_type": "rotation",
      "flags": {},
      "attributes": {},
      "kie_linking": [],
      "direction": 6.004885648174476
    },
    {
      "label": "spinach",
      "score": null,
      "points": [
        [
          158.36730498728997,
          546.6760363389582
        ],
        [
          172.69096703685966,
          538.8509840975973
        ],
        [
          174.74332648870637,
          542.6078028747434
        ],
        [
          160.41966443913674,
          550.4328551161042
        ]
      ],
      "group_id": null,
      "description": "",
      "difficult": false,
      "shape_type": "rotation",
      "flags": {},
      "attributes": {},
      "kie_linking": [],
      "direction": 5.783185307179588
    },
    {
      "label": "spinach",
      "score": null,
      "points": [
        [
          194.1825121308558,
          531.3082909332503
        ],
        [
          202.66072838318166,
          529.8529472737048
        ],
        [
          203.1343283582089,
          532.6119402985074
        ],
        [
          194.65611210588304,
          534.0672839580529
        ]
      ],
      "group_id": null,
      "description": "",
      "difficult": false,
      "shape_type": "rotation",
      "flags": {},
      "attributes": {},
      "kie_linking": [],
      "direction": 6.113185307179586
    },
    {
      "label": "spinach",
      "score": null,
      "points": [
        [
          204.85422755061688,
          524.1508751186584
        ],
        [
          210.35774810302394,
          525.9746835211599
        ],
        [
          204.30875576036863,
          544.2281105990784
        ],
        [
          198.80523520796157,
          542.4043021965769
        ]
      ],
      "group_id": null,
      "description": "",
      "difficult": false,
      "shape_type": "rotation",
      "flags": {},
      "attributes": {},
      "kie_linking": [],
      "direction": 0.32000000000000006
    },
    {
      "label": "spinach",
      "score": null,
      "points": [
        [
          244.17167736822398,
          620.0650673428905
        ],
        [
          251.4172464475846,
          625.1291322403895
        ],
        [
          242.47443762781188,
          637.9243353783231
        ],
        [
          235.22886854845137,
          632.8602704808242
        ]
      ],
      "group_id": null,
      "description": "",
      "difficult": false,
      "shape_type": "rotation",
      "flags": {},
      "attributes": {},
      "kie_linking": [],
      "direction": 0.61
    },
    {
      "label": "spinach",
      "score": null,
      "points": [
        [
          280.4638218923934,
          540.1576994434138
        ],
        [
          289.4812312369137,
          532.5624403306451
        ],
        [
          292.6405119042513,
          536.3132704983374
        ],
        [
          283.623102559731,
          543.908529611106
        ]
      ],
      "group_id": null,
      "description": "",
      "difficult": false,
      "shape_type": "rotation",
      "flags": {},
      "attributes": {},
      "kie_linking": [],
      "direction": 5.583185307179589
    },
    {
      "label": "spinach",
      "score": null,
      "points": [
        [
          273.9616406357982,
          464.8858823619114
        ],
        [
          280.7522123893805,
          460.2402022756005
        ],
        [
          282.8129203680155,
          463.25233077608283
        ],
        [
          276.0223486144333,
          467.8980108623938
        ]
      ],
      "group_id": null,
      "description": "",
      "difficult": false,
      "shape_type": "rotation",
      "flags": {},
      "attributes": {},
      "kie_linking": [],
      "direction": 5.683185307179588
    },
    {
      "kie_linking": [],
      "label": "gp",
      "score": null,
      "points": [
        [
          413.75,
          609.3526785714286
        ]
      ],
      "group_id": null,
      "description": "",
      "difficult": false,
      "shape_type": "point",
      "flags": {},
      "attributes": {}
    },
    {
      "kie_linking": [],
      "label": "gp",
      "score": null,
      "points": [
        [
          451.69642857142856,
          545.2901785714286
        ]
      ],
      "group_id": null,
      "description": "",
      "difficult": false,
      "shape_type": "point",
      "flags": {},
      "attributes": {}
    },
    {
      "kie_linking": [],
      "label": "gp",
      "score": null,
      "points": [
        [
          497.67857142857144,
          584.3526785714287
        ]
      ],
      "group_id": null,
      "description": "",
      "difficult": false,
      "shape_type": "point",
      "flags": {},
      "attributes": {}
    },
    {
      "kie_linking": [],
      "label": "gp",
      "score": null,
      "points": [
        [
          370.44642857142856,
          599.3080357142858
        ]
      ],
      "group_id": null,
      "description": "",
      "difficult": false,
      "shape_type": "point",
      "flags": {},
      "attributes": {}
    },
    {
      "kie_linking": [],
      "label": "gp",
      "score": null,
      "points": [
        [
          382.05357142857144,
          530.3348214285714
        ]
      ],
      "group_id": null,
      "description": "",
      "difficult": false,
      "shape_type": "point",
      "flags": {},
      "attributes": {}
    },
    {
      "kie_linking": [],
      "label": "gp",
      "score": null,
      "points": [
        [
          481.38392857142856,
          561.3616071428571
        ]
      ],
      "group_id": null,
      "description": "",
      "difficult": false,
      "shape_type": "point",
      "flags": {},
      "attributes": {}
    },
    {
      "kie_linking": [],
      "label": "gp",
      "score": null,
      "points": [
        [
          419.7767857142857,
          466.4955357142857
        ]
      ],
      "group_id": null,
      "description": "",
      "difficult": false,
      "shape_type": "point",
      "flags": {},
      "attributes": {}
    },
    {
      "kie_linking": [],
      "label": "gp",
      "score": null,
      "points": [
        [
          545.4464285714286,
          440.8258928571429
        ]
      ],
      "group_id": null,
      "description": "",
      "difficult": false,
      "shape_type": "point",
      "flags": {},
      "attributes": {}
    },
    {
      "kie_linking": [],
      "label": "gp",
      "score": null,
      "points": [
        [
          625.1339285714286,
          473.41517857142856
        ]
      ],
      "group_id": null,
      "description": "",
      "difficult": false,
      "shape_type": "point",
      "flags": {},
      "attributes": {}
    },
    {
      "kie_linking": [],
      "label": "gp",
      "score": null,
      "points": [
        [
          385.8482142857143,
          578.1026785714287
        ]
      ],
      "group_id": null,
      "description": "",
      "difficult": false,
      "shape_type": "point",
      "flags": {},
      "attributes": {}
    },
    {
      "kie_linking": [],
      "label": "gp",
      "score": null,
      "points": [
        [
          384.9553571428571,
          419.84375
        ]
      ],
      "group_id": null,
      "description": "",
      "difficult": false,
      "shape_type": "point",
      "flags": {},
      "attributes": {}
    },
    {
      "kie_linking": [],
      "label": "gp",
      "score": null,
      "points": [
        [
          450.5803571428571,
          427.20982142857144
        ]
      ],
      "group_id": null,
      "description": "",
      "difficult": false,
      "shape_type": "point",
      "flags": {},
      "attributes": {}
    },
    {
      "kie_linking": [],
      "label": "gp",
      "score": null,
      "points": [
        [
          596.5625,
          384.12946428571433
        ]
      ],
      "group_id": null,
      "description": "",
      "difficult": false,
      "shape_type": "point",
      "flags": {},
      "attributes": {}
    },
    {
      "kie_linking": [],
      "label": "gp",
      "score": null,
      "points": [
        [
          427.36607142857144,
          358.6830357142857
        ]
      ],
      "group_id": null,
      "description": "",
      "difficult": false,
      "shape_type": "point",
      "flags": {},
      "attributes": {}
    },
    {
      "kie_linking": [],
      "label": "gp",
      "score": null,
      "points": [
        [
          552.5892857142857,
          357.34375
        ]
      ],
      "group_id": null,
      "description": "",
      "difficult": false,
      "shape_type": "point",
      "flags": {},
      "attributes": {}
    },
    {
      "kie_linking": [],
      "label": "gp",
      "score": null,
      "points": [
        [
          341.42857142857144,
          350.2008928571429
        ]
      ],
      "group_id": null,
      "description": "",
      "difficult": false,
      "shape_type": "point",
      "flags": {},
      "attributes": {}
    },
    {
      "kie_linking": [],
      "label": "gp",
      "score": null,
      "points": [
        [
          499.46428571428567,
          491.4955357142857
        ]
      ],
      "group_id": null,
      "description": "",
      "difficult": false,
      "shape_type": "point",
      "flags": {},
      "attributes": {}
    },
    {
      "kie_linking": [],
      "label": "gp",
      "score": null,
      "points": [
        [
          628.9285714285713,
          603.7723214285714
        ]
      ],
      "group_id": null,
      "description": "",
      "difficult": false,
      "shape_type": "point",
      "flags": {},
      "attributes": {}
    },
    {
      "label": "sedge_weed",
      "score": null,
      "points": [
        [
          335.6988091200072,
          342.8310156273466
        ],
        [
          338.7494775206167,
          341.00235461757546
        ],
        [
          345.449591280654,
          352.1798365122616
        ],
        [
          342.3989228800444,
          354.0084975220327
        ]
      ],
      "group_id": null,
      "description": "",
      "difficult": false,
      "shape_type": "rotation",
      "flags": {},
      "attributes": {},
      "kie_linking": [],
      "direction": 5.743185307179587
    },
    {
      "label": "spinach",
      "score": null,
      "points": [
        [
          415.0,
          348.0
        ],
        [
          422.5,
          344.5
        ],
        [
          429.5,
          359.0
        ],
        [
          422.0,
          362.5
        ]
      ],
      "group_id": null,
      "description": "",
      "difficult": false,
      "shape_type": "rotation",
      "flags": {},
      "attributes": {},
      "kie_linking": [],
      "direction": 5.846558147366045
    },
    {
      "label": "spinach",
      "score": null,
      "points": [
        [
          397.5,
          595.0
        ],
        [
          410.5,
          592.0
        ],
        [
          418.0,
          624.0
        ],
        [
          405.5,
          627.0
        ]
      ],
      "group_id": null,
      "description": "",
      "difficult": false,
      "shape_type": "rotation",
      "flags": {},
      "attributes": {},
      "kie_linking": [],
      "direction": 6.056386459125701
    },
    {
      "label": "spinach",
      "score": null,
      "points": [
        [
          368.5,
          595.0
        ],
        [
          374.0,
          597.5
        ],
        [
          368.0,
          611.5
        ],
        [
          362.5,
          609.0
        ]
      ],
      "group_id": null,
      "description": "",
      "difficult": false,
      "shape_type": "rotation",
      "flags": {},
      "attributes": {},
      "kie_linking": [],
      "direction": 0.4266274931268761
    },
    {
      "label": "spinach",
      "score": null,
      "points": [
        [
          440.0,
          533.0
        ],
        [
          452.0,
          531.5
        ],
        [
          455.0,
          554.5
        ],
        [
          443.0,
          556.0
        ]
      ],
      "group_id": null,
      "description": "",
      "difficult": false,
      "shape_type": "rotation",
      "flags": {},
      "attributes": {},
      "kie_linking": [],
      "direction": 6.1588303126328245
    },
    {
      "label": "spinach",
      "score": null,
      "points": [
        [
          470.5,
          559.5
        ],
        [
          484.0,
          559.5
        ],
        [
          484.0,
          563.5
        ],
        [
          470.5,
          563.5
        ]
      ],
      "group_id": null,
      "description": "",
      "difficult": false,
      "shape_type": "rotation",
      "flags": {},
      "attributes": {},
      "kie_linking": [],
      "direction": 0.0
    },
    {
      "label": "spinach",
      "score": null,
      "points": [
        [
          505.0,
          578.5
        ],
        [
          507.0,
          583.0
        ],
        [
          486.0,
          590.5
        ],
        [
          484.5,
          586.0
        ]
      ],
      "group_id": null,
      "description": "",
      "difficult": false,
      "shape_type": "rotation",
      "flags": {},
      "attributes": {},
      "kie_linking": [],
      "direction": 1.1525719972156674
    },
    {
      "label": "spinach",
      "score": null,
      "points": [
        [
          391.0,
          573.5
        ],
        [
          392.0,
          576.5
        ],
        [
          381.5,
          580.5
        ],
        [
          380.5,
          577.5
        ]
      ],
      "group_id": null,
      "description": "",
      "difficult": false,
      "shape_type": "rotation",
      "flags": {},
      "attributes": {},
      "kie_linking": [],
      "direction": 1.2490457723982544
    },
    {
      "label": "spinach",
      "score": null,
      "points": [
        [
          360.02314814814815,
          530.787037037037
        ],
        [
          383.6978585919628,
          525.9879356423138
        ],
        [
          385.64466890825474,
          535.5918524459722
        ],
        [
          361.9699584644401,
          540.3909538406955
        ]
      ],
      "group_id": null,
      "description": "",
      "difficult": false,
      "shape_type": "rotation",
      "flags": {},
      "attributes": {},
      "kie_linking": [],
      "direction": 6.083185307179587
    },
    {
      "label": "spinach",
      "score": null,
      "points": [
        [
          403.0,
          458.0
        ],
        [
          409.0,
          452.0
        ],
        [
          425.5,
          468.5
        ],
        [
          419.5,
          474.5
        ]
      ],
      "group_id": null,
      "description": "",
      "difficult": false,
      "shape_type": "rotation",
      "flags": {},
      "attributes": {},
      "kie_linking": [],
      "direction": 5.497787143782138
    },
    {
      "label": "spinach",
      "score": null,
      "points": [
        [
          530.0,
          431.0
        ],
        [
          535.7926829268292,
          426.3658536585366
        ],
        [
          552.6707317073171,
          447.4634146341464
        ],
        [
          546.8780487804878,
          452.0975609756098
        ]
      ],
      "group_id": null,
      "description": "",
      "difficult": false,
      "shape_type": "rotation",
      "flags": {},
      "attributes": {},
      "kie_linking": [],
      "direction": 5.608444364956034
    },
    {
      "label": "spinach",
      "score": null,
      "points": [
        [
          440.31552076088735,
          419.5381716885373
        ],
        [
          444.77469417840354,
          416.52180839486044
        ],
        [
          455.4591734175162,
          432.3169700396565
        ],
        [
          451.0,
          435.3333333333333
        ]
      ],
      "group_id": null,
      "description": "",
      "difficult": false,
      "shape_type": "rotation",
      "flags": {},
      "attributes": {},
      "kie_linking": [],
      "direction": 5.688447030982882
    },
    {
      "label": "broadleaf_weed",
      "score": null,
      "points": [
        [
          383.46024533011365,
          415.3201746866713
        ],
        [
          387.25598445684716,
          415.70101892727405
        ],
        [
          386.33663366336634,
          424.86386138613864
        ],
        [
          382.54089453663283,
          424.4830171455359
        ]
      ],
      "group_id": null,
      "description": "",
      "difficult": false,
      "shape_type": "rotation",
      "flags": {},
      "attributes": {},
      "kie_linking": [],
      "direction": 0.1
    },
    {
      "label": "spinach",
      "score": null,
      "points": [
        [
          494.96983021019673,
          491.1230586052438
        ],
        [
          502.54818016085335,
          487.9189836368814
        ],
        [
          503.7100974570727,
          490.6671764761305
        ],
        [
          496.13174750641605,
          493.8712514444929
        ]
      ],
      "group_id": null,
      "description": "",
      "difficult": false,
      "shape_type": "rotation",
      "flags": {},
      "attributes": {},
      "kie_linking": [],
      "direction": 5.883185307179588
    },
    {
      "label": "spinach",
      "score": null,
      "points": [
        [
          562.0760233918129,
          352.3391812865497
        ],
        [
          551.1773173175984,
          359.4012697341738
        ],
        [
          542.1619190308543,
          345.4880800597712
        ],
        [
          553.0606251050688,
          338.42599161214713
        ]
      ],
      "group_id": null,
      "description": "",
      "difficult": false,
      "shape_type": "rotation",
      "flags": {},
      "attributes": {},
      "kie_linking": [],
      "direction": 2.566642340681727
    },
    {
      "label": "spinach",
      "score": null,
      "points": [
        [
          605.0,
          371.5
        ],
        [
          609.0,
          377.5
        ],
        [
          591.5,
          389.5
        ],
        [
          587.5,
          383.0
        ]
      ],
      "group_id": null,
      "description": "",
      "difficult": false,
      "shape_type": "rotation",
      "flags": {},
      "attributes": {},
      "kie_linking": [],
      "direction": 0.982793723247329
    },
    {
      "label": "spinach",
      "score": null,
      "points": [
        [
          633.0,
          466.0
        ],
        [
          635.0,
          470.0
        ],
        [
          620.5,
          476.5
        ],
        [
          618.5,
          472.5
        ]
      ],
      "group_id": null,
      "description": "",
      "difficult": false,
      "shape_type": "rotation",
      "flags": {},
      "attributes": {},
      "kie_linking": [],
      "direction": 1.1071487177940904
    },
    {
      "label": "sedge_weed",
      "score": null,
      "points": [
        [
          626.7935273808673,
          599.7959920354573
        ],
        [
          632.5,
          603.7
        ],
        [
          630.9327610967412,
          605.9908267529963
        ],
        [
          625.2262884776086,
          602.0868187884537
        ]
      ],
      "group_id": null,
      "description": "",
      "difficult": false,
      "shape_type": "rotation",
      "flags": {},
      "attributes": {},
      "kie_linking": [],
      "direction": 0.6
    }
  ],
  "imagePath": "mosaic_0082_IMG_20251212132738719_right__IMG_20251212132742027_left__IMG_20251212132742027_right__IMG_20251212132745404_left.jpg",
  "imageData": null,
  "imageHeight": 640,
  "imageWidth": 640,
  "description": "mosaic"
}